<?xml version="1.0" encoding="utf-8" ?>
<dwsync>
<file name="FFsoul.jpg" server="headinghomek9rescue.com" local="131301397700000000" remote="132947182200000000" Dst="2" />
<file name="FFNYres.jpg" server="headinghomek9rescue.com" local="130030499660000000" remote="132947182200000000" Dst="2" />
<file name="FFname.jpg" server="headinghomek9rescue.com" local="131409358900000000" remote="132947182200000000" Dst="2" />
<file name="FFmomshome.jpg" server="headinghomek9rescue.com" local="130508571420000000" remote="132947182200000000" Dst="2" />
<file name="FFlove.jpg" server="headinghomek9rescue.com" local="130789677920000000" remote="132947182200000000" Dst="2" />
<file name="FFholidays.jpg" server="headinghomek9rescue.com" local="130949245120000000" remote="132947182200000000" Dst="2" />
<file name="FFhangout.jpg" server="headinghomek9rescue.com" local="131472621080000000" remote="132947182200000000" Dst="2" />
<file name="FFgoodpeople.jpg" server="headinghomek9rescue.com" local="130789677940000000" remote="132947182200000000" Dst="2" />
<file name="FFfillheart.jpg" server="headinghomek9rescue.com" local="131301395660000000" remote="132947182200000000" Dst="2" />
<file name="FFdogwarts.jpg" server="headinghomek9rescue.com" local="130346623840000000" remote="132947182200000000" Dst="2" />
<file name="FFdoglove.jpg" server="headinghomek9rescue.com" local="130842641900000000" remote="132947182200000000" Dst="2" />
<file name="FFdoglivesshort.jpg" server="headinghomek9rescue.com" local="131163168620000000" remote="132947182200000000" Dst="2" />
<file name="FFdogfetchlove.jpg" server="headinghomek9rescue.com" local="131665496498469332" remote="132947182200000000" Dst="2" />
<file name="FFdidntdoit.jpg" server="headinghomek9rescue.com" local="130789677920000000" remote="132947182200000000" Dst="2" />
<file name="FFconfetti.jpg" server="headinghomek9rescue.com" local="132067691456181311" remote="132947182200000000" Dst="2" />
<file name="FFadoptanother.jpg" server="headinghomek9rescue.com" local="131181972960000000" remote="132947182200000000" Dst="2" />
</dwsync>